README.rst
setup.py
lrucache/__init__.py
lrucache/lru_cache.py
lrucache/memoize_decorator.py
lrucache/utils/__init__.py
lrucache/utils/cache_decorator.py
lrucache/utils/cache_doublylinkedlist.py
lrucache/utils/cache_node.py
lrucache/utils/cache_thread.py
timedLruCache.egg-info/PKG-INFO
timedLruCache.egg-info/SOURCES.txt
timedLruCache.egg-info/dependency_links.txt
timedLruCache.egg-info/top_level.txt