Metadata-Version: 1.1
Name: timedLruCache
Version: 1.0.1
Summary: A time constraint LRUCache Implementation
Home-page: https://github.com/andela-sjames/timed-lru-cache
Author: Samuel James
Author-email: samuelvarejames@gmail.com
License: MIT
Keywords: timed lru cache implementation
Platform: UNKNOWN
Classifier: Intended Audience :: Developers
Classifier: License :: OSI Approved :: MIT License
Classifier: Programming Language :: Python :: 3
